fluxo_ofx_parse/__init__.py
fluxo_ofx_parse/mcc.py
fluxo_ofx_parse/ofxerrors.py
fluxo_ofx_parse/ofxparse.py
fluxo_ofx_parse/ofxprinter.py
fluxo_ofx_parse/ofxutil.py
fluxo_ofx_parse-0.1.0.dist-info/LICENSE
fluxo_ofx_parse-0.1.0.dist-info/METADATA
fluxo_ofx_parse-0.1.0.dist-info/WHEEL
fluxo_ofx_parse-0.1.0.dist-info/top_level.txt
fluxo_ofx_parse-0.1.0.dist-info/RECORD
