Metadata-Version: 2.1
Name: fluxo-ofx-parse
Version: 0.1.0
Summary: Python parser that converts Open Financial Exchange (OFX) to python objects.
Home-page: https://github.com/Fluxo-Resultados/fluxo-ofx-parser
Author: Brenno Flavio
Author-email: brenno.flavio@fluxoresultados.com.br
License: UNKNOWN
Platform: UNKNOWN
Classifier: Programming Language :: Python :: 3
Classifier: License :: OSI Approved :: MIT License
Classifier: Operating System :: OS Independent
Requires-Python: >=3.6
Requires-Dist: beautifulsoup4 (==4.9.3)
